{"nodes": [{"id": "readme_chatbot", "label": "CLI-Based Consultancy Chatbot", "file_type": "document", "source_file": "README.md"}, {"id": "intent_detection", "label": "Intent Detection", "file_type": "concept", "source_file": "README.md"}, {"id": "domain_router", "label": "Domain Router", "file_type": "concept", "source_file": "README.md"}], "edges": [{"source": "main_py", "target": "chatbot_logic", "relation": "calls", "confidence": "EXTRACTED", "confidence_score": 1.0, "source_file": "README.md"}, {"source": "chatbot_logic", "target": "intent_detection", "relation": "implements", "confidence": "INFERRED", "confidence_score": 0.9, "source_file": "README.md"}, {"source": "chatbot_logic", "target": "domain_router", "relation": "implements", "confidence": "INFERRED", "confidence_score": 0.9, "source_file": "README.md"}, {"source": "domain_router", "target": "prompts_education", "relation": "references", "confidence": "EXTRACTED", "confidence_score": 1.0, "source_file": "README.md"}, {"source": "domain_router", "target": "prompts_finance", "relation": "references", "confidence": "EXTRACTED", "confidence_score": 1.0, "source_file": "README.md"}, {"source": "domain_router", "target": "prompts_healthcare", "relation": "references", "confidence": "EXTRACTED", "confidence_score": 1.0, "source_file": "README.md"}, {"source": "chatbot_logic", "target": "chatbot_memory_db", "relation": "shares_data_with", "confidence": "EXTRACTED", "confidence_score": 1.0, "source_file": "README.md"}], "hyperedges": []}